ngspice_tools/__init__.py
ngspice_tools/ngspice_input.py
ngspice_tools/plot_colors.py
ngspice_tools/plot_sim.py
ngspice_tools-0.0.1.dist-info/METADATA
ngspice_tools-0.0.1.dist-info/WHEEL
ngspice_tools-0.0.1.dist-info/entry_points.txt
ngspice_tools-0.0.1.dist-info/top_level.txt
ngspice_tools-0.0.1.dist-info/RECORD
